poyonga/__init__.py
poyonga/client.py
poyonga/const.py
poyonga/result.py
poyonga-0.6.0.dist-info/LICENSE
poyonga-0.6.0.dist-info/METADATA
poyonga-0.6.0.dist-info/WHEEL
poyonga-0.6.0.dist-info/top_level.txt
poyonga-0.6.0.dist-info/RECORD
