Metadata-Version: 2.1
Name: poyonga
Version: 0.6.0
Summary: Python Groonga Client
Author-email: Hideo Hattori <hhatto.jp@gmail.com>
License: Copyright (c) 2012-2019 Hideo Hattori
Project-URL: Repository, https://github.com/hhatto/poyonga
Keywords: groonga,http,gqtp
Classifier: Development Status :: 5 - Production/Stable
Classifier: Intended Audience :: Developers
Classifier: Operating System :: Unix
Classifier: Operating System :: POSIX :: Linux
Classifier: Operating System :: MacOS :: MacOS X
Classifier: Programming Language :: Python
Classifier: Programming Language :: Python :: 3
Requires-Python: >=3.8
License-File: LICENSE
Provides-Extra: dev
Requires-Dist: ruff ; extra == 'dev'
Requires-Dist: pytest ; extra == 'dev'
Requires-Dist: black ; extra == 'dev'
